setup.cfg
setup.py
phovea_clustering/__init__.py
phovea_clustering/clustering_affinity.py
phovea_clustering/clustering_api.py
phovea_clustering/clustering_fuzzy.py
phovea_clustering/clustering_hierarchical.py
phovea_clustering/clustering_kmeans.py
phovea_clustering/clustering_service.py
phovea_clustering/clustering_util.py
phovea_clustering/config.json
phovea_clustering.egg-info/PKG-INFO
phovea_clustering.egg-info/SOURCES.txt
phovea_clustering.egg-info/dependency_links.txt
phovea_clustering.egg-info/entry_points.txt
phovea_clustering.egg-info/not-zip-safe
phovea_clustering.egg-info/requires.txt
phovea_clustering.egg-info/top_level.txt